<routes>
  <vehicle id="vehicle_0" type="car">
    <stop lat="12.9092" lon="77.5666" />
    <stop lat="12.9092" lon="77.5666" />
  </vehicle>
  <vehicle id="vehicle_1" type="car">
    <stop lat="12.9092" lon="77.5666" />
    <stop lat="12.9092" lon="77.5666" />
  </vehicle>
  <vehicle id="vehicle_2" type="car">
    <stop lat="12.9092" lon="77.5666" />
    <stop lat="12.9092" lon="77.5666" />
  </vehicle>
  <vehicle id="vehicle_3" type="car">
    <stop lat="12.9092" lon="77.5666" />
    <stop lat="12.9092" lon="77.5666" />
  </vehicle>
  <vehicle id="vehicle_4" type="car">
    <stop lat="12.9092" lon="77.5666" />
    <stop lat="12.9082017810137" lon="77.5670138567961" />
    <stop lat="12.9092" lon="77.5666" />
  </vehicle>
  <vehicle id="vehicle_5" type="car">
    <stop lat="12.9092" lon="77.5666" />
    <stop lat="12.9112305034943" lon="77.5656030794626" />
    <stop lat="12.9039886057683" lon="77.5645965664268" />
    <stop lat="12.9052189331475" lon="77.562928544173" />
    <stop lat="12.9100311228611" lon="77.5613488101178" />
    <stop lat="12.905223808311" lon="77.5623235348138" />
    <stop lat="12.9112940084608" lon="77.5630409963828" />
    <stop lat="12.9113147937642" lon="77.5640191995633" />
    <stop lat="12.9058553162592" lon="77.562402892853" />
    <stop lat="12.9070811065017" lon="77.5596998633955" />
    <stop lat="12.9061489181435" lon="77.5673464360759" />
    <stop lat="12.9060598999626" lon="77.5660855351062" />
    <stop lat="12.9085682459312" lon="77.5648996449005" />
    <stop lat="12.9064071254588" lon="77.5599678532332" />
    <stop lat="12.9125355785084" lon="77.5594909476387" />
    <stop lat="12.9092" lon="77.5666" />
  </vehicle>
  <vehicle id="vehicle_6" type="car">
    <stop lat="12.9092" lon="77.5666" />
    <stop lat="12.9053692987516" lon="77.5678297234957" />
    <stop lat="12.9049160671413" lon="77.5618063883477" />
    <stop lat="12.9104097366291" lon="77.565038529759" />
    <stop lat="12.9088215239552" lon="77.5655427198657" />
    <stop lat="12.908033684518" lon="77.5598672482068" />
    <stop lat="12.9078110181246" lon="77.5645689353017" />
    <stop lat="12.9086309730125" lon="77.5639568112052" />
    <stop lat="12.908990201991" lon="77.5625931436857" />
    <stop lat="12.9066505974377" lon="77.561779840125" />
    <stop lat="12.9052739063218" lon="77.5667266815797" />
    <stop lat="12.9075836914619" lon="77.5638356259731" />
    <stop lat="12.9088756911048" lon="77.5597133624114" />
    <stop lat="12.9085345391154" lon="77.5653813866571" />
    <stop lat="12.9076500815644" lon="77.5623276469127" />
    <stop lat="12.9037181961191" lon="77.5639410794138" />
    <stop lat="12.9113988811512" lon="77.563204932979" />
    <stop lat="12.909458957185" lon="77.5611209164545" />
    <stop lat="12.9091228301672" lon="77.5681606605476" />
    <stop lat="12.9090495013499" lon="77.5601985498368" />
    <stop lat="12.9097321994472" lon="77.5682874255389" />
    <stop lat="12.9092" lon="77.5666" />
  </vehicle>
  <vehicle id="vehicle_7" type="car">
    <stop lat="12.9092" lon="77.5666" />
    <stop lat="12.9039522347718" lon="77.5612141027721" />
    <stop lat="12.9053124507519" lon="77.5660816459822" />
    <stop lat="12.9037362847339" lon="77.5639697946331" />
    <stop lat="12.9092843231765" lon="77.567866330398" />
    <stop lat="12.9087169737282" lon="77.5628141590711" />
    <stop lat="12.9097851192714" lon="77.5595807645607" />
    <stop lat="12.9095704867213" lon="77.5607158380533" />
    <stop lat="12.9096594598593" lon="77.5654195533712" />
    <stop lat="12.9040348710204" lon="77.5685756139219" />
    <stop lat="12.9080579069532" lon="77.5682389621509" />
    <stop lat="12.9078594717032" lon="77.5640793189429" />
    <stop lat="12.9115363466846" lon="77.5686067585063" />
    <stop lat="12.9070542661573" lon="77.5668746134767" />
    <stop lat="12.9068588922116" lon="77.5654688432631" />
    <stop lat="12.9065833601907" lon="77.5678356994391" />
    <stop lat="12.9088868570595" lon="77.5621071180982" />
    <stop lat="12.904510343382" lon="77.567161105858" />
    <stop lat="12.9059252973712" lon="77.5653250331107" />
    <stop lat="12.9037673259832" lon="77.5677101727852" />
    <stop lat="12.9092" lon="77.5666" />
  </vehicle>
  <vehicle id="vehicle_8" type="car">
    <stop lat="12.9092" lon="77.5666" />
    <stop lat="12.9110869206687" lon="77.5615502304652" />
    <stop lat="12.9051311874429" lon="77.5677596828288" />
    <stop lat="12.9045538858592" lon="77.5595082300493" />
    <stop lat="12.9052047300592" lon="77.567847255306" />
    <stop lat="12.9115475346211" lon="77.5613161726735" />
    <stop lat="12.9096313163118" lon="77.5651841615522" />
    <stop lat="12.90797587614" lon="77.565316920142" />
    <stop lat="12.9113399709252" lon="77.5660068191243" />
    <stop lat="12.9059390498247" lon="77.5647828139339" />
    <stop lat="12.9076530387274" lon="77.5675691503376" />
    <stop lat="12.9038459543042" lon="77.5668663017278" />
    <stop lat="12.9049423307721" lon="77.560200165538" />
    <stop lat="12.9050394302476" lon="77.56804295383" />
    <stop lat="12.9075904626899" lon="77.5667523583757" />
    <stop lat="12.9124145390974" lon="77.5681209321902" />
    <stop lat="12.9038376952224" lon="77.5676814870595" />
    <stop lat="12.9092" lon="77.5666" />
  </vehicle>
  <vehicle id="vehicle_9" type="car">
    <stop lat="12.9092" lon="77.5666" />
    <stop lat="12.9098288370393" lon="77.5605659139142" />
    <stop lat="12.9043736144641" lon="77.5617650483098" />
    <stop lat="12.9081732577776" lon="77.567090513195" />
    <stop lat="12.908981985794" lon="77.5681452427054" />
    <stop lat="12.9050190633112" lon="77.5650443095686" />
    <stop lat="12.9107053705811" lon="77.5604643413442" />
    <stop lat="12.9040254054211" lon="77.5672226403074" />
    <stop lat="12.9123602487339" lon="77.5619000847754" />
    <stop lat="12.9061009580518" lon="77.562286162801" />
    <stop lat="12.9088266848982" lon="77.5627198621401" />
    <stop lat="12.9096972720067" lon="77.5680621472056" />
    <stop lat="12.9126931595391" lon="77.5659384397029" />
    <stop lat="12.9112866662906" lon="77.562271245904" />
    <stop lat="12.9094103542086" lon="77.5671232426027" />
    <stop lat="12.9090328733843" lon="77.5682355978935" />
    <stop lat="12.9040898853316" lon="77.5607236981214" />
    <stop lat="12.9044910311316" lon="77.5655091371582" />
    <stop lat="12.90385310739" lon="77.5620813123884" />
    <stop lat="12.9092538800072" lon="77.5604073534256" />
    <stop lat="12.9109477476168" lon="77.5652388375294" />
    <stop lat="12.9092" lon="77.5666" />
  </vehicle>
</routes>
